fractvol/__init__.py
fractvol/core.py
fractvol/detect.py
fractvol/signal.py
fractvol/visualize.py
fractvol-0.1.0.dist-info/licenses/LICENSE
fractvol-0.1.0.dist-info/METADATA
fractvol-0.1.0.dist-info/WHEEL
fractvol-0.1.0.dist-info/top_level.txt
fractvol-0.1.0.dist-info/RECORD
